ngrammer_keras/__init__.py
ngrammer_keras/ngrammer_keras.py
ngrammer_keras-0.1.1.dist-info/LICENSE
ngrammer_keras-0.1.1.dist-info/WHEEL
ngrammer_keras-0.1.1.dist-info/METADATA
ngrammer_keras-0.1.1.dist-info/RECORD
